swirl_cli/__init__.py
swirl_cli/auth.py
swirl_cli/config.py
swirl_cli-0.1.2.dist-info/LICENSE
swirl_cli-0.1.2.dist-info/METADATA
swirl_cli-0.1.2.dist-info/WHEEL
swirl_cli-0.1.2.dist-info/top_level.txt
swirl_cli-0.1.2.dist-info/RECORD
