Metadata-Version: 2.1
Name: swirl-cli
Version: 0.1.2
Summary: Provides access to SWIRL CLI projects
Home-page: https://git.starlightconsultants.com/swirl/python-cli
Author: William Naslund
Author-email: admin@starlightconsultants.com
License: UNKNOWN
Platform: UNKNOWN
Classifier: Programming Language :: Python :: 3
Classifier: License :: OSI Approved :: MIT License
Classifier: Operating System :: OS Independent
